cookesgot/__init__.py
cookesgot/main.py
cookiesgetr/__init__.py
cookiesgetr/main.py
fmfocus/__init__.py
fmfocus/main.py
pyuer/__init__.py
pyuer/main.py
pyuer-0.1.0.dist-info/METADATA
pyuer-0.1.0.dist-info/WHEEL
pyuer-0.1.0.dist-info/top_level.txt
pyuer-0.1.0.dist-info/RECORD
